[
  {
    "query": "Explain the different parameter data types described in the manual",
    "timestamp": "2026-07-15T16:12:35.068345"
  },
  {
    "query": "thdh",
    "timestamp": "2026-07-17T09:15:30.768121"
  },
  {
    "query": "what is parameter 0020",
    "timestamp": "2026-07-18T08:41:39.791358"
  },
  {
    "query": "what are its features",
    "timestamp": "2026-07-18T08:42:44.065088"
  },
  {
    "query": "what is 6501",
    "timestamp": "2026-07-18T09:11:43.540080"
  },
  {
    "query": "what is parameter 0020",
    "timestamp": "2026-07-20T10:07:09.293104"
  },
  {
    "query": "what is spindle alarm",
    "timestamp": "2026-07-20T10:08:45.079265"
  },
  {
    "query": "what is its parameter no.",
    "timestamp": "2026-07-20T10:10:52.772198"
  },
  {
    "query": "what is parameter 0020",
    "timestamp": "2026-07-20T10:46:27.391578"
  },
  {
    "query": "what is parameter 0020",
    "timestamp": "2026-07-20T10:48:27.681661"
  },
  {
    "query": "what is parameter 0020",
    "timestamp": "2026-07-20T11:00:23.615900"
  },
  {
    "query": "what is parameter 0020",
    "timestamp": "2026-07-20T11:08:06.472514"
  },
  {
    "query": "what is parameter 0020",
    "timestamp": "2026-07-20T11:26:14.760123"
  },
  {
    "query": "what is parameter 0020",
    "timestamp": "2026-07-20T11:44:44.876133"
  },
  {
    "query": "what is parameter 0020",
    "timestamp": "2026-07-20T11:53:17.467981"
  },
  {
    "query": "what is spindle alarm",
    "timestamp": "2026-07-20T15:05:22.279693"
  },
  {
    "query": "what is parameter 0020",
    "timestamp": "2026-07-20T15:44:33.287542"
  },
  {
    "query": "Explain the parameter representation table for Bit, Bit Path, Bit Axis, Machine Group, Axis, and Spindle data types",
    "timestamp": "2026-07-21T11:12:35.539890"
  },
  {
    "query": "Create a table showing parameters 6071 through 6084 and the program each one calls.",
    "timestamp": "2026-07-21T11:24:26.436248"
  },
  {
    "query": "Find every table related to M codes in the manual and summarize each one into a clean markdown table.",
    "timestamp": "2026-07-21T11:25:59.372490"
  }
]